django_encryption/__init__.py
django_encryption/fields.py
django_encryption/management/__init__.py
django_encryption/management/commands/__init__.py
django_encryption/management/commands/generate_vault_migration.py
django_encryption/py.typed
django_encryption/vault_wrapper.py
django_encryption-0.3.48.dist-info/METADATA
django_encryption-0.3.48.dist-info/WHEEL
django_encryption-0.3.48.dist-info/RECORD
